oslo_policy_opa/__init__.py
oslo_policy_opa/generator.py
oslo_policy_opa/neutron.py
oslo_policy_opa/neutron_policy_hook.py
oslo_policy_opa/opa.py
oslo_policy_opa/opts.py
oslo_policy_opa/version.py
oslo_policy_opa/tests/test_generator.py
oslo_policy_opa-0.2.0.dist-info/licenses/AUTHORS
oslo_policy_opa-0.2.0.dist-info/licenses/LICENSE
oslo_policy_opa-0.2.0.dist-info/METADATA
oslo_policy_opa-0.2.0.dist-info/WHEEL
oslo_policy_opa-0.2.0.dist-info/entry_points.txt
oslo_policy_opa-0.2.0.dist-info/pbr.json
oslo_policy_opa-0.2.0.dist-info/top_level.txt
oslo_policy_opa-0.2.0.dist-info/RECORD
