Metadata-Version: 2.4
Name: oslo.policy.opa
Version: 0.2.0
Summary: Perform a OpenPolicyAgent check
Author-email: Artem Goncharov <artem.goncharov@gmail.com>
Requires-Python: >=3.9
License-File: LICENSE
License-File: AUTHORS
Requires-Dist: oslo.log>=6
Requires-Dist: oslo.policy>=4
Requires-Dist: requests>2.30
Provides-Extra: generate
Requires-Dist: barbican; extra == "generate"
Requires-Dist: cinder; extra == "generate"
Requires-Dist: designate; extra == "generate"
Requires-Dist: glance; extra == "generate"
Requires-Dist: keystone; extra == "generate"
Requires-Dist: neutron; extra == "generate"
Requires-Dist: nova; extra == "generate"
Requires-Dist: octavia; extra == "generate"
Dynamic: license-file
